toktokkie/Directory.py
toktokkie/__init__.py
toktokkie/exceptions.py
toktokkie/check/BookChecker.py
toktokkie/check/BookSeriesChecker.py
toktokkie/check/Checker.py
toktokkie/check/MangaChecker.py
toktokkie/check/MovieChecker.py
toktokkie/check/TvSeriesChecker.py
toktokkie/check/VisualNovelChecker.py
toktokkie/check/__init__.py
toktokkie/check/map.py
toktokkie/gui/MainWindow.py
toktokkie/gui/__init__.py
toktokkie/gui/pyuic/__init__.py
toktokkie/gui/pyuic/book_widget.py
toktokkie/gui/pyuic/main.py
toktokkie/gui/pyuic/movie_widget.py
toktokkie/gui/pyuic/tv_season_widget.py
toktokkie/gui/pyuic/tv_show_widget.py
toktokkie/gui/qt_designer/__init__.py
toktokkie/gui/widgets/BookWidget.py
toktokkie/gui/widgets/MovieWidget.py
toktokkie/gui/widgets/TvSeasonWidget.py
toktokkie/gui/widgets/TvSeriesWidget.py
toktokkie/gui/widgets/__init__.py
toktokkie/iconizing/Iconizer.py
toktokkie/iconizing/__init__.py
toktokkie/iconizing/procedures/GnomeProcedure.py
toktokkie/iconizing/procedures/NoopProcedure.py
toktokkie/iconizing/procedures/Procedure.py
toktokkie/iconizing/procedures/__init__.py
toktokkie/metadata/Book.py
toktokkie/metadata/BookSeries.py
toktokkie/metadata/Manga.py
toktokkie/metadata/Metadata.py
toktokkie/metadata/Movie.py
toktokkie/metadata/TvSeries.py
toktokkie/metadata/VisualNovel.py
toktokkie/metadata/__init__.py
toktokkie/metadata/components/BookVolume.py
toktokkie/metadata/components/MetadataPart.py
toktokkie/metadata/components/TvEpisode.py
toktokkie/metadata/components/TvEpisodeRange.py
toktokkie/metadata/components/TvSeason.py
toktokkie/metadata/components/__init__.py
toktokkie/metadata/components/enums.py
toktokkie/metadata/helper/__init__.py
toktokkie/metadata/helper/functions.py
toktokkie/renaming/RenameOperation.py
toktokkie/renaming/Renamer.py
toktokkie/renaming/__init__.py
toktokkie/scripts/AnilistOpenCommand.py
toktokkie/scripts/ArchiveCommand.py
toktokkie/scripts/CheckCommand.py
toktokkie/scripts/Command.py
toktokkie/scripts/GuiCommand.py
toktokkie-0.18.0.dist-info/LICENSE
toktokkie-0.18.0.dist-info/METADATA
toktokkie-0.18.0.dist-info/WHEEL
toktokkie-0.18.0.dist-info/top_level.txt
toktokkie-0.18.0.dist-info/RECORD
