Metadata-Version: 2.1
Name: toktokkie
Version: 0.18.0
Summary: A media manager for downloading and organizing files
Home-page: https://gitlab.namibsun.net/namibsun/python/toktokkie
Author: Hermann Krumrey
Author-email: hermann@krumreyh.com
License: GNU GPL3
Platform: UNKNOWN
Classifier: License :: OSI Approved :: GNU General Public License v3 (GPLv3)
Requires-Dist: tvdb-api
Requires-Dist: beautifulsoup4
Requires-Dist: typing
Requires-Dist: requests
Requires-Dist: xdcc-dl
Requires-Dist: colorama
Requires-Dist: anime-list-apis
Requires-Dist: mutagen
Requires-Dist: puffotter
Requires-Dist: manga-dl
Provides-Extra: gui
Requires-Dist: PyQt5 ; extra == 'gui'
